django_clamd/__init__.py
django_clamd/conf.py
django_clamd/validators.py
django_clamd/locale/bg/LC_MESSAGES/django.mo
django_clamd/locale/bg/LC_MESSAGES/django.po
django_clamd/locale/de/LC_MESSAGES/django.mo
django_clamd/locale/de/LC_MESSAGES/django.po
django_clamd/locale/en/LC_MESSAGES/django.mo
django_clamd/locale/en/LC_MESSAGES/django.po
django_clamd/tests/__init__.py
django_clamd/tests/forms.py
django_clamd/tests/settings.py
django_clamd/tests/test.py
django_clamd-1.0.0.dist-info/METADATA
django_clamd-1.0.0.dist-info/WHEEL
django_clamd-1.0.0.dist-info/top_level.txt
django_clamd-1.0.0.dist-info/RECORD
