Metadata-Version: 2.1
Name: django-clamd
Version: 1.0.0
Summary: django-clamd is a django integration with Clamd (Clamav daemon).
Home-page: https://github.com/vstoykov/django-clamd
Download-URL: https://github.com/vstoykov/django-clamd/releases
Author: Venelin Stoykov
Author-email: vkstoykov@gmail.com
Maintainer: Venelin Stoykov
Maintainer-email: vkstoykov@gmail.com
Keywords: python,django,clamav,antivirus,scanner,virus,libclamav,clamd
Classifier: Development Status :: 5 - Production/Stable
Classifier: Environment :: Web Environment
Classifier: Framework :: Django
Classifier: Framework :: Django :: 3.2
Classifier: Framework :: Django :: 4.2
Classifier: Framework :: Django :: 5.0
Classifier: Intended Audience :: Developers
Classifier: License :: OSI Approved :: GNU Library or Lesser General Public License (LGPL)
Classifier: Operating System :: OS Independent
Classifier: Programming Language :: Python
Classifier: Programming Language :: Python :: 3
Classifier: Programming Language :: Python :: 3.7
Classifier: Programming Language :: Python :: 3.8
Classifier: Programming Language :: Python :: 3.9
Classifier: Programming Language :: Python :: 3.9
Classifier: Programming Language :: Python :: 3.10
Classifier: Programming Language :: Python :: 3.11
Classifier: Programming Language :: Python :: 3.12
Requires-Dist: clamd
Requires-Dist: Django >=1.4
